quick_deploy/__init__.py
quick_deploy/cli.py
quick_deploy/triton_template.py
quick_deploy/utils.py
quick_deploy/backend/__init__.py
quick_deploy/backend/common.py
quick_deploy/backend/skl_ort.py
quick_deploy/backend/tf_ort.py
quick_deploy/backend/torch_ort.py
quick_deploy/backend/transformers_ort.py
quick_deploy/backend/xgb_ort.py
quick_deploy-0.2.2.data/data/LICENSE
quick_deploy-0.2.2.data/data/README.md
quick_deploy-0.2.2.data/data/VERSION
quick_deploy-0.2.2.dist-info/LICENSE
quick_deploy-0.2.2.dist-info/METADATA
quick_deploy-0.2.2.dist-info/WHEEL
quick_deploy-0.2.2.dist-info/entry_points.txt
quick_deploy-0.2.2.dist-info/top_level.txt
quick_deploy-0.2.2.dist-info/RECORD
