Metadata-Version: 2.1
Name: quick-deploy
Version: 0.2.2
Summary: Quick-Deploy optimize and deploy Machine Learning models as fast inference API.
Home-page: https://github.com/rodrigobaron/quick-deploy
Author: Rodrigo Baron
Author-email: baron.rodrigo0@gmail.com
License: Apache
Platform: UNKNOWN
Classifier: Intended Audience :: Developers
Classifier: Intended Audience :: Science/Research
Classifier: License :: OSI Approved :: Apache Software License
Classifier: Operating System :: OS Independent
Classifier: Programming Language :: Python :: 3
Classifier: Programming Language :: Python :: 3.7
Classifier: Programming Language :: Python :: 3.8
Classifier: Programming Language :: Python :: 3.9
Classifier: Topic :: Scientific/Engineering :: Artificial Intelligence
Requires-Python: >=3.7
License-File: LICENSE
Requires-Dist: numpy (==1.21.5)
Requires-Dist: pyaml (==21.10.1)
Requires-Dist: types-PyYAML (==6.0.1)
Requires-Dist: onnxruntime (==1.10.0)
Requires-Dist: onnxruntime-tools (==1.7.0)
Requires-Dist: onnxmltools (==1.10.0)
Requires-Dist: sympy (==1.9.0)
Requires-Dist: unidecode (==1.3.2)
Provides-Extra: all
Requires-Dist: torch (==1.10.1) ; extra == 'all'
Requires-Dist: tensorflow (>=2.3) ; extra == 'all'
Requires-Dist: tf2onnx (==1.9.3) ; extra == 'all'
Requires-Dist: transformers (==4.15.0) ; extra == 'all'
Requires-Dist: scikit-learn (==1.0.1) ; extra == 'all'
Requires-Dist: skl2onnx (==1.9.0) ; extra == 'all'
Requires-Dist: xgboost (==1.5.1) ; extra == 'all'
Provides-Extra: build
Requires-Dist: python-build (==0.2.13) ; extra == 'build'
Requires-Dist: coverage-badge (==1.1.0) ; extra == 'build'
Requires-Dist: build (==0.7.0) ; extra == 'build'
Requires-Dist: pytest (==6.2.5) ; extra == 'build'
Requires-Dist: pytest-cov (==3.0.0) ; extra == 'build'
Requires-Dist: mock (==4.0.3) ; extra == 'build'
Requires-Dist: black (==21.12b0) ; extra == 'build'
Requires-Dist: flake8 (==4.0.1) ; extra == 'build'
Requires-Dist: mypy (==0.930) ; extra == 'build'
Requires-Dist: isort (==5.10.1) ; extra == 'build'
Requires-Dist: torch (==1.10.1) ; extra == 'build'
Requires-Dist: tensorflow (>=2.3) ; extra == 'build'
Requires-Dist: tf2onnx (==1.9.3) ; extra == 'build'
Requires-Dist: transformers (==4.15.0) ; extra == 'build'
Requires-Dist: scikit-learn (==1.0.1) ; extra == 'build'
Requires-Dist: skl2onnx (==1.9.0) ; extra == 'build'
Requires-Dist: xgboost (==1.5.1) ; extra == 'build'
Provides-Extra: dev
Requires-Dist: pytest (==6.2.5) ; extra == 'dev'
Requires-Dist: pytest-cov (==3.0.0) ; extra == 'dev'
Requires-Dist: mock (==4.0.3) ; extra == 'dev'
Requires-Dist: black (==21.12b0) ; extra == 'dev'
Requires-Dist: flake8 (==4.0.1) ; extra == 'dev'
Requires-Dist: mypy (==0.930) ; extra == 'dev'
Requires-Dist: isort (==5.10.1) ; extra == 'dev'
Requires-Dist: torch (==1.10.1) ; extra == 'dev'
Requires-Dist: tensorflow (>=2.3) ; extra == 'dev'
Requires-Dist: tf2onnx (==1.9.3) ; extra == 'dev'
Requires-Dist: transformers (==4.15.0) ; extra == 'dev'
Requires-Dist: scikit-learn (==1.0.1) ; extra == 'dev'
Requires-Dist: skl2onnx (==1.9.0) ; extra == 'dev'
Requires-Dist: xgboost (==1.5.1) ; extra == 'dev'
Provides-Extra: sklearn
Requires-Dist: scikit-learn (==1.0.1) ; extra == 'sklearn'
Requires-Dist: skl2onnx (==1.9.0) ; extra == 'sklearn'
Provides-Extra: tf
Requires-Dist: tensorflow (>=2.3) ; extra == 'tf'
Requires-Dist: tf2onnx (==1.9.3) ; extra == 'tf'
Provides-Extra: torch
Requires-Dist: torch (==1.10.1) ; extra == 'torch'
Provides-Extra: transformers
Requires-Dist: transformers (==4.15.0) ; extra == 'transformers'
Requires-Dist: torch (==1.10.1) ; extra == 'transformers'
Requires-Dist: tensorflow (>=2.3) ; extra == 'transformers'
Requires-Dist: tf2onnx (==1.9.3) ; extra == 'transformers'
Provides-Extra: xgboost
Requires-Dist: xgboost (==1.5.1) ; extra == 'xgboost'
Requires-Dist: scikit-learn (==1.0.1) ; extra == 'xgboost'
Requires-Dist: skl2onnx (==1.9.0) ; extra == 'xgboost'
